traveltimemap/__init__.py
traveltimemap/direction.py
traveltimemap/excel.py
traveltimemap/map.py
traveltimemap/tasks.py
traveltimemap/timestamp.py
traveltimemap-1.0.7.dist-info/LICENSE
traveltimemap-1.0.7.dist-info/METADATA
traveltimemap-1.0.7.dist-info/WHEEL
traveltimemap-1.0.7.dist-info/top_level.txt
traveltimemap-1.0.7.dist-info/RECORD
