Metadata-Version: 2.1
Name: traveltimemap
Version: 1.0.7
Summary: Travel Time Map
Home-page: https://github.com/nguyen-huong/traveltime/
Author: Huong Nguyen
Author-email: huongmng@usc.edu
Classifier: Programming Language :: Python :: 3
Classifier: License :: OSI Approved :: MIT License
Classifier: Operating System :: OS Independent
Requires-Python: >=3.6
License-File: LICENSE
Requires-Dist: folium
Requires-Dist: pandas
Requires-Dist: geopy
Requires-Dist: numpy
Requires-Dist: matplotlib
Requires-Dist: datetime
Requires-Dist: openpyxl
Requires-Dist: IPython
Requires-Dist: geopandas
